[
  { "id": 1, "name": "American" },
  { "id": 2, "name": "Australian" },
  { "id": 3, "name": "Brazilian" },
  { "id": 4, "name": "British" },
  { "id": 5, "name": "Canadian" },
  { "id": 6, "name": "Chinese" },
  { "id": 7, "name": "French" },
  { "id": 8, "name": "German" },
  { "id": 9, "name": "Indian" },
  { "id": 10, "name": "Indonesian" },
  { "id": 11, "name": "Italian" },
  { "id": 12, "name": "Japanese" },
  { "id": 13, "name": "Korean" },
  { "id": 14, "name": "Malaysian" },
  { "id": 15, "name": "Mexican" },
  { "id": 16, "name": "Russian" },
  { "id": 17, "name": "Singaporean" },
  { "id": 18, "name": "South African" },
  { "id": 19, "name": "Spanish" },
  { "id": 20, "name": "Turkish" }
]
